{"constitution_charter.md":"b8f18851","constitution_first-charter-revised.md":"c19f8f8c","constitution_first-charter.md":"3f0cce4f","constitution_secound-charter.md":"5e323e8b","constitution_treaties.md":"2d387f67","culture_index.md":"95a01cbc","deadletters.md":"6687f6b7","government_conventions.md":"b873490b","government_council-acts_first.md":"57395288","government_council-acts_intro.md":"f43e586a","government_council-acts_precursor.md":"403750aa","government_introduction.md":"e2ee5605","government_procedures.md":"d12d8b1e","index.md":"dac89433"}
